{"name":"Amira","title":"Fallen Maiden","gender":"female","obtain":"","five_star":"yes","rarity":"SSR","element":"Light","type":"Special","race":"Unknown","join_weapon":"Dragon Slayer","weapon":"Dragon Slayer","attack":{"min_atk":"1620","max_atk":"8650","flb_atk":"","bonus_atk":""},"hp":{"min_hp":"275","max_hp":"1470","flb_hp":"","bonus_hp":""},"ougi":{"ougi1_name":"Avantesia","ougi1_desc":"450% Light damage to a foe.","ougi2_name":"Inhuman Rampage","ougi2_desc":"500% Light damage to a foe ","ougi3_name":"","ougi3_desc":"","ougi4_name":"","ougi4_desc":""},"skill":{"a1_name":"Bal","a2_name":"Power Within","a3_name":"Half","a4_name":""},"ability":{"sa_name":"One","sa_desc":"Charge bar fills up 20% faster.","sa2_name":"Hidden Key","sa2_desc":"'''While in Half","sa_emp_desc":""},"wiki_link":"https:/gbf.wiki/Amira"}