{"name":"Charioce XVII","title":"Determined Resolution","gender":"male","obtain":"","five_star":"no","rarity":"SSR","element":"Fire","type":"Special","race":"Human","join_weapon":"","weapon":"Sabre","attack":{"min_atk":"","max_atk":"7400","flb_atk":"","bonus_atk":""},"hp":{"min_hp":"","max_hp":"1700","flb_hp":"","bonus_hp":""},"ougi":{"ougi1_name":"A Farewell to Arms","ougi1_desc":"Unworldly Fire damage to a foe and remove 3 buffs. Charioce XVII self","ougi2_name":"","ougi2_desc":"","ougi3_name":"","ougi3_desc":"","ougi4_name":"","ougi4_desc":""},"skill":{"a1_name":"Boost Morale","a2_name":"Fire Command","a3_name":"Activate Dromos","a4_name":""},"ability":{"sa_name":"I Fear No Gods, nor Demons","sa_desc":"Gain 1 ","sa2_name":"","sa2_desc":"","sa_emp_desc":""},"wiki_link":"https:/gbf.wiki/Charioce XVII"}