{"name":"The Sterling Spear","title":"Returned Soldier","gender":"male","obtain":"","five_star":"","rarity":"SR","element":"Dark","type":"Defense","race":"Human","join_weapon":"","weapon":"Spear","attack":{"min_atk":"1000","max_atk":"4830","flb_atk":"","bonus_atk":""},"hp":{"min_hp":"240","max_hp":"1330","flb_hp":"","bonus_hp":""},"ougi":{"ougi1_name":"The Sterling Spear","ougi1_desc":"Big Dark damage to a foe.","ougi2_name":"","ougi2_desc":"","ougi3_name":"","ougi3_desc":"","ougi4_name":"","ougi4_desc":""},"skill":{"a1_name":"Counterpoint","a2_name":"Valiant Shield","a3_name":"Demoralize","a4_name":""},"ability":{"sa_name":"Imperial Cuirass","sa_desc":"Chance to cut damage taken by 50%.","sa2_name":"","sa2_desc":"","sa_emp_desc":""},"wiki_link":"https:/gbf.wiki/Deliford (SR)"}