{"name":"Drang","title":"Azure Mercenary","gender":"male","obtain":"","five_star":"no","rarity":"SSR","element":"Water","type":"Special","race":"Erune","join_weapon":"Blue Sphere","weapon":"Blue Sphere","attack":{"min_atk":"1470","max_atk":"7510","flb_atk":"","bonus_atk":""},"hp":{"min_hp":"230","max_hp":"1250","flb_hp":"","bonus_hp":""},"ougi":{"ougi1_name":"Unhappy Hour","ougi1_desc":"Massive Water damage to a foe. Inflict ","ougi2_name":"","ougi2_desc":"","ougi3_name":"","ougi3_desc":"","ougi4_name":"","ougi4_desc":""},"skill":{"a1_name":"Fair Trick","a2_name":"Switcheroo","a3_name":"Fool You Thrice","a4_name":""},"ability":{"sa_name":"On a Roll","sa_desc":"Gain stackable ","sa2_name":"","sa2_desc":"","sa_emp_desc":""},"wiki_link":"https:/gbf.wiki/Drang"}